version_demo/__init__.py
version_demo/akg.py
version_demo-0.0.3.dist-info/METADATA
version_demo-0.0.3.dist-info/WHEEL
version_demo-0.0.3.dist-info/top_level.txt
version_demo-0.0.3.dist-info/RECORD
