Metadata-Version: 2.1
Name: version-demo
Version: 0.0.3
Summary: Just demo for checking how is version work
Home-page: https://bitbucket.org/avneesh111995/mrchantintionpythonlibrary/
Author: avneesh gupta
Author-email: avneesh.gupta@paytm.com
License: UNKNOWN
Platform: UNKNOWN
Classifier: Programming Language :: Python :: 3
Classifier: Operating System :: OS Independent
